bufr.py
setup.py
table-B.txt
test.py
PyBUFR.egg-info/PKG-INFO
PyBUFR.egg-info/SOURCES.txt
PyBUFR.egg-info/dependency_links.txt
PyBUFR.egg-info/requires.txt
PyBUFR.egg-info/top_level.txt
PyBUFR.egg-info/zip-safe
bin/bufrdump