Metadata-Version: 1.0
Name: PyBUFR
Version: 0.4
Summary: Pure Python library to encode and decode BUFR.
Home-page: https://bitbucket.org/castelao/pybufr
Author: Guilherme Castelao, Roberto de Almeida, Luiz Irber
Author-email: guilherme@castelao.net, roberto@dealmeida.net, luiz.irber@gmail.com
License: PSF
Download-URL: http://cheeseshop.python.org/packages/source/P/PyBUFR/PyBUFR-0.4.tar.gz
Platform: any
Classifier: Development Status :: 3 - Alpha
Classifier: Environment :: Console
Classifier: Intended Audience :: Developers
Classifier: Intended Audience :: Science/Research
Classifier: License :: OSI Approved :: Python Software Foundation License
Classifier: Operating System :: OS Independent
Classifier: Programming Language :: Python
Classifier: Programming Language :: Python :: 2
Classifier: Topic :: Scientific/Engineering
Classifier: Topic :: Software Development :: Libraries :: Python Modules
